jobinfo/__init__.py
jobinfo/main.py
jobinfo-1.0.11.dist-info/licenses/LICENSE
jobinfo-1.0.11.dist-info/METADATA
jobinfo-1.0.11.dist-info/WHEEL
jobinfo-1.0.11.dist-info/entry_points.txt
jobinfo-1.0.11.dist-info/top_level.txt
jobinfo-1.0.11.dist-info/RECORD
