Metadata-Version: 2.4
Name: jobinfo
Version: 1.0.11
Summary: This tool extracts useful information about scheduled jobs.
Author-email: Mohammad Zandsalimy <mohammad.91225@gmail.com>
License-Expression: MIT
Project-URL: Homepage, https://github.com/ahama92/jobinfo
Project-URL: Bug Tracker, https://github.com/ahama92/jobinfo/issues
Classifier: Programming Language :: Python :: 3
Classifier: Operating System :: OS Independent
Classifier: Intended Audience :: Science/Research
Classifier: Topic :: Scientific/Engineering
Requires-Python: >=3.6
License-File: LICENSE
Requires-Dist: cowsay>=6.0
Requires-Dist: tabulate>=0.8
Dynamic: license-file
